AutoCAD/AutoCAD_Module.py
AutoCAD/__init__.py
AutoCAD/__main__.py
autocad-0.1.9.dist-info/licenses/LICENSE
autocad-0.1.9.dist-info/METADATA
autocad-0.1.9.dist-info/WHEEL
autocad-0.1.9.dist-info/entry_points.txt
autocad-0.1.9.dist-info/top_level.txt
autocad-0.1.9.dist-info/RECORD
