Metadata-Version: 2.4
Name: AutoCAD
Version: 0.1.9
Summary: A professional AutoCAD automation package with many functions.
Home-page: https://github.com/Jones-peter
Author: Jones Peter
Author-email: jonespetersoftware@gmail.com
License: MIT
Project-URL: Homepage, https://github.com/Jones-peter/AutoCAD
Project-URL: Documentation, https://autocad-automation.readthedocs.io/
Project-URL: Bug Tracker, https://github.com/Jones-peter/AutoCAD/issues
Keywords: autocad,automation,activex,comtypes,AutoCAD,AutoCADlib
Classifier: Programming Language :: Python :: 3
Classifier: License :: OSI Approved :: MIT License
Classifier: Intended Audience :: Developers
Classifier: Intended Audience :: System Administrators
Classifier: Operating System :: Microsoft :: Windows
License-File: LICENSE
Requires-Dist: psutil
Dynamic: author
Dynamic: author-email
Dynamic: classifier
Dynamic: description
Dynamic: description-content-type
Dynamic: home-page
Dynamic: keywords
Dynamic: license
Dynamic: license-file
Dynamic: project-url
Dynamic: requires-dist
Dynamic: summary
